{"bJp0fDF7DtxwLGcbrCwZHw==":"jeremy-wong-308974-2000x1333.jpg","apMS0nK9BgWKzaOl0auGMg==":"max-felner-379612-2000x1333.jpg","3FXz4lFvYHVp6D4mOLeqCw==":"jason-blackeye-127871-2000x1333.jpg","CCL4scWDk4/W9UV4UpP0qA==":"ander-burdain-180587-2000x1333.jpg","5n1sO/VpzeP8s1bp9UM05w==":"mbr-1920x1080.jpg","8iJRpxVT5LK9Txj+CBftiA==":"freddy-marschall-186923-2000x1333.jpg","GuCAHd5yMjB9Ap2wwBqZLg==":"aaditya-kalia-332803--4000x4000.jpg","LK+1DM1wVSk0QQ3SfT4f7Q==":"diego-ph-254975-3456x3456.jpg","9Ejz0bYjrUAQTKV/1YIarw==":"gerrie-van-der-walt-338444-2000x2000.jpg","hgQuyfvt1QWPXZPS0i512g==":"alex-iby-280624-2000x1333.jpg","Nw97EY0aw1N7Uulgq0HjLg==":"filip-mroz-250497-3221x4169.jpg","u9k6lUfB0poe9UYWjHlvCg==":"guilherme-stecanella-370401-2000x1333.jpg","82YAxBc/+DOP3sExkqmmCg==":"max-felner-379613-2000x1333.jpg","FyK8SVOags3o+laB14hc1A==":"igor-son-320878-1999x1501.jpg","LFCy6uJtLljlE19aGfBg+w==":"igor-son-320878.jpg","z1f68YvMrbzVpnEKz/4OdA==":"myles-tan-85939.jpg","V5JFG1pGqSKVyYkw+EUgtw==":"gaelle-marcel-85383.jpg","oZY6ntFcWUM1a3d4ePAL5A==":"tanalee-youngblood-341695.jpg","nvekSGU4zlHdO2HtKONOPA==":"annie-spratt-370997.jpg","2MeA1FfpTwNySvxlkVdUWg==":"devan-freeman-2166.jpg","yk/nYPIPr2rgoh19LYCt+Q==":"imani-clovis-252739.jpg","LKKr+ziyRph1lsBMjrCdYA==":"alexa-mazzarello-223414.jpg","diqD6p5JH5bCJN/4pyt7BQ==":"gwen-weustink-123644.jpg","grNggV5GGp3KOnCHg6feOA==":"daniel-hjalmarsson-269425.jpg","3VDq4w/ZQYTYlg5kzxEJ7A==":"samuel-zeller-62819.jpg","3Tgc5U4KO03WMk+f7M2aJA==":".png","QSwwtwbC2fJI8nNQeJE2IQ==":"16.png","HVYCI0C2CPWodHBpanZ2pA==":"3.png","267b6UTzKG1rtGk2YBO+aQ==":"34.png","nRnjjLZeumbsiKPUnQRC3Q==":"-4.png","yhW7ilVqsrIyhcCsQO/dsw==":"17.png","z2l/F+U3oRuu87dx4qa6sA==":"18.png","h/aLZ1UZiyaImROaVs6org==":"19.png","9HHVGM04/DkMJxlQ8+WZ6Q==":"20.png","cL1X9zcFl9dnJBLxnwLgbQ==":"product1.jpg","kaAoq6RQJm6Z1/ZqvRtQtA==":"background2.jpg","EB03g4BAU1sqDkrZsJYQwA==":"-10.png","jjBf5W2i1qrmFsi5wBG1gQ==":"7.png","CnBA5Tm4qGCGrNerJ20MuQ==":"8.png","BLGBu6+m6CVPHdr1NQFUVg==":"9.png","jB43aXiwThARKVM0Sjmq8w==":"-11.png","+9aG5/jC7vgzZ32HO3GxJw==":"8-1.png","06gM5m7/8WbldbPB1kuaEQ==":"10-1.png","7Nci6hDLEox9F88B0RIH3Q==":"11-1.png","yKkBhmiUFnxLkvqcj3mmqA==":"-12.png","JpISRPB4R3L3fZMAKIeb4w==":"12-1.png","/ghcdTUP835SnDHIDFS8fA==":"10-2.png","Qp4KBf57x+3DW69YmKVa2Q==":"11-2.png","Oy54/Qnfnlx+VLiTsCl6bg==":"-1.png","Ys4Q1ZDqFE256hjwntoGSQ==":"-2.png","RGeoP0E5OfxzL3xVcQtrPA==":"-3.png","yRA62ss6EGIntiyrbiURsg==":"-5.png","53MC6aVr6vk+DgEYBfcMyg==":"-16.png","J9MVjNbxESfDlEOIUXbi4w==":"-24.png","3yiTpjVMjQ7DNZIOjtHk0Q==":"-19.png","QtDll5UZbbguVypr/3q6Rg==":"15.png","gxM1ceWUOqGt0D6vEQpqzg==":"15-1.png","iXkxGfALxrxt8QzAfB+K1A==":"15-2.png","tjJO+dd7h6/ZtRA9AtbUUg==":"-17.png","aNF8NBPQXCZTtVNHx2i3dg==":"-25.png","9uZThh/vQyr/uTRcyjgrLg==":"-20.png","s2gpC90KBHbcXqdNbu0Fnw==":"-18.png","SHbJ+87fd0IRLmsB6ClW5A==":"-27.png","OpCC8BMu5qqOBY9nYbTwXw==":"-23.png","kgwhHFeveAwb/zvNGdseaQ==":"-22.png","YLfiFHGEYJ5CamZEU0tsMQ==":"-26.png","UBgPebyg9ZvBbqC2uAx8Jw==":"-21.png","hMF49v0pgDfLDQXiZI/1Gg==":"29.png","+hY8l3nUrZP28NYlQT4dmQ==":"1.png","HV5ekEKa0QJd/VVY8tYRPQ==":"2.png","PN5oh4S5Dbn4EkcWanHOnw==":"3-1.png","WF89ZGEos4PoowmPW7gNhg==":"-6.png","uZZ87ReoFsBN+Ew/kmU3WA==":"-7.png","U2E3XqjAc3xSUgUOliLqUQ==":"-8.png","YvhywY5uXMq6MKZXNVzImA==":"-9.png","mU9U5bAhabkkLBrr01KfBg==":"img-5287.jpeg","fHwXVwxr6BJTSZJv0F0ZCg==":"-13.png","NmLCReL98Zb+oHuyuMG0JQ==":"-14.png","2bjbQHW9aqzEZW8lZmJs1Q==":"28-1.png","1Yd31qmDjXtSpxUsK/qjXg==":"-28.png","nxyzZ17uEijnN25OwbD8Xg==":"-29.png","P9e0jKSGtFvKFVs6b/4u9g==":"img-5288.jpeg","/pDHuRRWDAuSqTd3h85u6w==":"img-5282.jpg","JXihw6SrDJeqUlEdVnzoKQ==":"img-5289.jpeg","Dt2rmhSm4qHKq6SklKnjMg==":"img-5282.jpeg","lhTqUgnxi8eTJfYMEC8uuA==":"1-1.png","SWqelbveLafP9VvIEGyikw==":"1-2.png","W1x0R5lv8akWvt5EJsg+9g==":"t.png"}